README.md
setup.cfg
setup.py
nomad_envoy_cli/__init__.py
nomad_envoy_cli/api_client.py
nomad_envoy_cli/append_alibaba_headers.py
nomad_envoy_cli/configuration.py
nomad_envoy_cli/exceptions.py
nomad_envoy_cli/rest.py
nomad_envoy_cli/rest_bak.py
nomad_envoy_cli/swagger_validator.py
nomad_envoy_cli.egg-info/PKG-INFO
nomad_envoy_cli.egg-info/SOURCES.txt
nomad_envoy_cli.egg-info/dependency_links.txt
nomad_envoy_cli.egg-info/requires.txt
nomad_envoy_cli.egg-info/top_level.txt
nomad_envoy_cli/api/__init__.py
nomad_envoy_cli/api/customs_api.py
nomad_envoy_cli/api/customs_callback_api.py
nomad_envoy_cli/api/order_api.py
nomad_envoy_cli/api/product_api.py
nomad_envoy_cli/api/store_api.py
nomad_envoy_cli/models/__init__.py
nomad_envoy_cli/models/address.py
nomad_envoy_cli/models/api_response.py
nomad_envoy_cli/models/api_response_connector_response.py
nomad_envoy_cli/models/api_response_data.py
nomad_envoy_cli/models/api_response_data_required.py
nomad_envoy_cli/models/api_response_general.py
nomad_envoy_cli/models/api_response_inventory.py
nomad_envoy_cli/models/api_response_required.py
nomad_envoy_cli/models/base_api_response.py
nomad_envoy_cli/models/base_api_response_data.py
nomad_envoy_cli/models/customs_declaration_result.py
nomad_envoy_cli/models/gender.py
nomad_envoy_cli/models/images.py
nomad_envoy_cli/models/inventory.py
nomad_envoy_cli/models/order.py
nomad_envoy_cli/models/order_api_response.py
nomad_envoy_cli/models/order_api_response_data.py
nomad_envoy_cli/models/order_api_response_data_required.py
nomad_envoy_cli/models/order_api_response_required.py
nomad_envoy_cli/models/order_product.py
nomad_envoy_cli/models/product.py
nomad_envoy_cli/models/product_api_response.py
nomad_envoy_cli/models/product_api_response_data.py
nomad_envoy_cli/models/product_api_response_required.py
nomad_envoy_cli/models/product_component.py
nomad_envoy_cli/models/product_response_data_required.py
nomad_envoy_cli/models/product_sku.py
nomad_envoy_cli/models/store.py
test/test_address.py
test/test_api_response.py
test/test_api_response_connector_response.py
test/test_api_response_data.py
test/test_api_response_data_required.py
test/test_api_response_general.py
