Metadata-Version: 2.1
Name: nomad-envoy-cli
Version: 1.58.0
Summary: Nomad Envoy
Home-page: UNKNOWN
Author: OpenAPI Generator community
Author-email: paul@samarkand.global
License: UNKNOWN
Keywords: OpenAPI,OpenAPI-Generator,Nomad Envoy
Platform: UNKNOWN
